atorch/atorch_addon.py
atorch_addon-0.0.1.dist-info/METADATA
atorch_addon-0.0.1.dist-info/WHEEL
atorch_addon-0.0.1.dist-info/top_level.txt
atorch_addon-0.0.1.dist-info/RECORD
